peewee_extras.py
peewee_extras-0.5.0.dist-info/METADATA
peewee_extras-0.5.0.dist-info/RECORD
peewee_extras-0.5.0.dist-info/WHEEL
peewee_extras-0.5.0.dist-info/top_level.txt
