Metadata-Version: 2.1
Name: peewee-extras
Version: 0.5.0
Summary: Extras for Peewee
Home-page: https://github.com/foxx/peewee-extras
Author: Cal Leeming
Author-email: cal@iops.io
License: UNKNOWN
Keywords: peewee
Platform: UNKNOWN
Requires-Dist: peewee (>=3.2)
Requires-Dist: six
